{
  "name": "Qtimestamp",
  "options": {
    "idInjection": true
  },
  "mongodb": {
    "collection": "qtimestamps"
  },
  "properties": {
    "CID": {
      "type": "String"
    },
    "QTID": {
      "type": "String"
    },
    "QTSID": {
      "type": "Number"
    },
    "CaseNo": {
      "type": "Number"
    },
    "CMPlanNo": {
      "type": "Number"
    },
    "StaffID": {
      "type": "String"
    },
    "UpdateTime": {
      "type": "Date"
    },
    "ConfirmID": {
      "type": "Number"
    },
    "ConfirmTime": {
      "type": "Date"
    },
    "HostID": {
      "type": "String"
    },
    "RecordDate": {
      "type": "Date"
    },
    "InputType": {
      "type": "Number"
    },
    "id": {
      "type": "Number"
    }
  }
}