{
  "name": "Tumbonlatlong",
  "options": {
    "idInjection": false,
    "mssql": {
      "schema": "dbo",
      "table": "TumbonLatLong"
    }
  },
  "properties": {
    "tumbonid": {
      "type": "String",
      "required": true,
      "length": 6,
      "precision": null,
      "scale": null,
      "id": 1,
      "mssql": {
        "columnName": "TumbonID",
        "dataType": "varchar",
        "dataLength": 6,
        "dataPrecision": null,
        "dataScale": null,
        "nullable": "NO"
      }
    },
    "lat": {
      "type": "String",
      "required": true,
      "length": 40,
      "precision": null,
      "scale": null,
      "id": 2,
      "mssql": {
        "columnName": "Lat",
        "dataType": "varchar",
        "dataLength": 40,
        "dataPrecision": null,
        "dataScale": null,
        "nullable": "NO"
      }
    },
    "long": {
      "type": "String",
      "required": true,
      "length": 40,
      "precision": null,
      "scale": null,
      "id": 3,
      "mssql": {
        "columnName": "Long",
        "dataType": "varchar",
        "dataLength": 40,
        "dataPrecision": null,
        "dataScale": null,
        "nullable": "NO"
      }
    },
    "numberofseries": {
      "type": "Number",
      "required": true,
      "length": null,
      "precision": 10,
      "scale": 0,
      "id": 4,
      "mssql": {
        "columnName": "NumberOfSeries",
        "dataType": "int",
        "dataLength": null,
        "dataPrecision": 10,
        "dataScale": 0,
        "nullable": "NO"
      }
    }
  }
}