{
  "name": "WelfarePerson",
  "options": {
    "idInjection": false,
    "mssql": {
      "schema": "dbo",
      "table": "WelfarePerson"
    }
  },
  "properties": {
    "cid": {
      "type": "String",
      "required": true,
      "length": 13,
      "precision": null,
      "scale": null,
      "id": 1,
      "mssql": {
        "columnName": "CID",
        "dataType": "varchar",
        "dataLength": 13,
        "dataPrecision": null,
        "dataScale": null,
        "nullable": "NO"
      }
    },
    "welfareid": {
      "type": "String",
      "required": true,
      "length": 50,
      "precision": null,
      "scale": null,
      "id": 2,
      "mssql": {
        "columnName": "WelfareID",
        "dataType": "varchar",
        "dataLength": 50,
        "dataPrecision": null,
        "dataScale": null,
        "nullable": "NO"
      }
    },
    "hostid": {
      "type": "String",
      "required": true,
      "length": 50,
      "precision": null,
      "scale": null,
      "id": 3,
      "mssql": {
        "columnName": "HostID",
        "dataType": "varchar",
        "dataLength": 50,
        "dataPrecision": null,
        "dataScale": null,
        "nullable": "NO"
      }
    },
    "recdate": {
      "type": "Date",
      "required": true,
      "length": null,
      "precision": null,
      "scale": null,
      "id": 4,
      "mssql": {
        "columnName": "RecDate",
        "dataType": "date",
        "dataLength": null,
        "dataPrecision": null,
        "dataScale": null,
        "nullable": "NO"
      }
    }
  }
}
